hybrid_query_client/__init__.py
hybrid_query_client/client.py
hybrid_query_client-1.0.0.dist-info/METADATA
hybrid_query_client-1.0.0.dist-info/WHEEL
hybrid_query_client-1.0.0.dist-info/top_level.txt
hybrid_query_client-1.0.0.dist-info/RECORD
