Metadata-Version: 2.4
Name: hybrid_query_client
Version: 1.0.0
Summary: Socket client for NL hybrid query engine
Dynamic: summary
